django_auto_starter/__init__.py
django_auto_starter/core.py
django_auto_starter-0.1.1.dist-info/licenses/LICENSE
django_auto_starter-0.1.1.dist-info/METADATA
django_auto_starter-0.1.1.dist-info/WHEEL
django_auto_starter-0.1.1.dist-info/entry_points.txt
django_auto_starter-0.1.1.dist-info/top_level.txt
django_auto_starter-0.1.1.dist-info/RECORD
