Metadata-Version: 2.4
Name: django-auto-starter
Version: 0.1.1
Summary: CLI tool to auto-start Django projects with REST setup
Author-email: Enoch Jason J <enochjason06@gmail.com>
License: Proprietary — All rights reserved by Enoch Jason J
License-File: LICENSE
Requires-Dist: yaspin
Dynamic: license-file
